knowledge_graph_mcp/__init__.py
knowledge_graph_mcp/server.py
knowledge_graph_mcp/database/__init__.py
knowledge_graph_mcp/database/connection.py
knowledge_graph_mcp/database/schema.py
knowledge_graph_mcp/models/__init__.py
knowledge_graph_mcp/models/edge.py
knowledge_graph_mcp/models/enums.py
knowledge_graph_mcp/models/node.py
knowledge_graph_mcp/services/__init__.py
knowledge_graph_mcp/services/graph_service.py
knowledge_graph_mcp/services/mermaid_generator.py
knowledge_graph_mcp/services/query_engine.py
knowledge_graph_mcp/services/spaced_repetition.py
knowledge_graph_mcp-0.1.0.dist-info/METADATA
knowledge_graph_mcp-0.1.0.dist-info/WHEEL
knowledge_graph_mcp-0.1.0.dist-info/entry_points.txt
knowledge_graph_mcp-0.1.0.dist-info/licenses/LICENSE
knowledge_graph_mcp-0.1.0.dist-info/RECORD
