Metadata-Version: 2.4
Name: knowledge-graph-mcp
Version: 0.1.0
Summary: MCP server for tracking student learning via a knowledge graph
Project-URL: Homepage, https://github.com/zcsabbagh/knowledge-graph-mcp
Project-URL: Repository, https://github.com/zcsabbagh/knowledge-graph-mcp
Author: zcsabbagh
License-Expression: MIT
License-File: LICENSE
Keywords: education,knowledge-graph,learning,mcp,spaced-repetition
Classifier: Development Status :: 4 - Beta
Classifier: Intended Audience :: Developers
Classifier: License :: OSI Approved :: MIT License
Classifier: Programming Language :: Python :: 3
Classifier: Programming Language :: Python :: 3.10
Classifier: Programming Language :: Python :: 3.11
Classifier: Programming Language :: Python :: 3.12
Requires-Python: >=3.10
Requires-Dist: fastmcp>=2.0.0
Requires-Dist: pydantic>=2.0.0
